jenkins_backup_s3/__init__.py
jenkins_backup_s3/backup.py
jenkins_backup_s3-0.1.9.dist-info/LICENSE
jenkins_backup_s3-0.1.9.dist-info/METADATA
jenkins_backup_s3-0.1.9.dist-info/WHEEL
jenkins_backup_s3-0.1.9.dist-info/entry_points.txt
jenkins_backup_s3-0.1.9.dist-info/top_level.txt
jenkins_backup_s3-0.1.9.dist-info/RECORD
