Metadata-Version: 2.1
Name: jenkins-backup-s3
Version: 0.1.9
Summary: Backup Jenkins to S3
Home-page: http://github.com/artsy/jenkins-backup-s3
Author: Isac Petruzzi
Author-email: isac@artsymail.com
License: MIT
Platform: UNKNOWN
Requires-Dist: boto3 (~=1.9)
Requires-Dist: click (~=7.0)
Requires-Dist: colorama (~=0.4)
Requires-Dist: python-dateutil (~=2.8)
Requires-Dist: termcolor (~=1.1)
